django_health_check_plus-1.0.0.dist-info/METADATA
django_health_check_plus-1.0.0.dist-info/RECORD
django_health_check_plus-1.0.0.dist-info/WHEEL
django_health_check_plus-1.0.0.dist-info/top_level.txt
health_check_plus/__init__.py
health_check_plus/tests.py
health_check_plus/urls.py
health_check_plus/views.py
