Metadata-Version: 2.1
Name: django-health-check-plus
Version: 1.0.0
Summary: Django package to improve usage of django-health-check library.
Home-page: https://github.com/emigue/django-health-check-plus
Author: Miguel Angel Moreno
Author-email: emigue@gmail.com
License: GPLv3
Keywords: python,django,health,check,network,service
Platform: UNKNOWN
Classifier: Development Status :: 4 - Beta
Classifier: Framework :: Django
Classifier: Intended Audience :: Developers
Classifier: License :: OSI Approved :: GNU General Public License v3 (GPLv3)
Classifier: Natural Language :: English
Classifier: Programming Language :: Python :: 2
Classifier: Programming Language :: Python :: 2.6
Classifier: Programming Language :: Python :: 2.7
Classifier: Programming Language :: Python :: 3
Classifier: Programming Language :: Python :: 3.6
Classifier: Topic :: Software Development :: Libraries :: Python Modules
Requires-Dist: django-health-check (==2.3.0)
